html_sanitizer_with_iframe.py
HTML_Sanitizer_With_IFrame-0.1.0.dist-info/RECORD
HTML_Sanitizer_With_IFrame-0.1.0.dist-info/DESCRIPTION.rst
HTML_Sanitizer_With_IFrame-0.1.0.dist-info/top_level.txt
HTML_Sanitizer_With_IFrame-0.1.0.dist-info/METADATA
HTML_Sanitizer_With_IFrame-0.1.0.dist-info/WHEEL
HTML_Sanitizer_With_IFrame-0.1.0.dist-info/metadata.json
