Metadata-Version: 2.0
Name: HTML-Sanitizer-With-IFrame
Version: 0.1.0
Summary: Extends Python html5lib's sanitizer.HTMLSanitizer to allow iframe elements.
Home-page: https://github.com/Jaza/html-sanitizer-with-iframe
Author: Jeremy Epstein
Author-email: jazepstein@gmail.com
License: UNKNOWN
Platform: any
Classifier: Development Status :: 2 - Pre-Alpha
Classifier: Environment :: Web Environment
Classifier: Intended Audience :: Developers
Classifier: Operating System :: OS Independent
Classifier: Programming Language :: Python
Classifier: Programming Language :: Python :: 2
Classifier: Programming Language :: Python :: 2.7
Classifier: Programming Language :: Python :: 3
Classifier: Programming Language :: Python :: 3.3
Requires-Dist: html5lib
